gac/__init__.py
gac/__version__.py
gac/ai.py
gac/cli.py
gac/config.py
gac/config_cli.py
gac/constants.py
gac/diff_cli.py
gac/errors.py
gac/git.py
gac/init_cli.py
gac/main.py
gac/preprocess.py
gac/prompt.py
gac/utils.py
gac_dev-0.14.9.dist-info/METADATA
gac_dev-0.14.9.dist-info/WHEEL
gac_dev-0.14.9.dist-info/entry_points.txt
gac_dev-0.14.9.dist-info/licenses/LICENSE
gac_dev-0.14.9.dist-info/RECORD
