Metadata-Version: 2.4
Name: gac-dev
Version: 0.14.9
Summary: git auto commit
Project-URL: Documentation, https://github.com/criteria-dev/gac#readme
Project-URL: Issues, https://github.com/criteria-dev/gac/issues
Project-URL: Source, https://github.com/criteria-dev/gac
Author-email: cellwebb <cellwebb@users.noreply.github.com>
License-Expression: MIT
License-File: LICENSE
Classifier: Development Status :: 4 - Beta
Classifier: Programming Language :: Python
Classifier: Programming Language :: Python :: 3.10
Classifier: Programming Language :: Python :: 3.11
Classifier: Programming Language :: Python :: 3.12
Classifier: Programming Language :: Python :: 3.13
Classifier: Programming Language :: Python :: Implementation :: CPython
Classifier: Programming Language :: Python :: Implementation :: PyPy
Requires-Python: >=3.10
Requires-Dist: aisuite
Requires-Dist: anthropic
Requires-Dist: black
Requires-Dist: click
Requires-Dist: docstring-parser
Requires-Dist: groq
Requires-Dist: halo
Requires-Dist: isort
Requires-Dist: ollama
Requires-Dist: openai
Requires-Dist: pydantic
Requires-Dist: python-dotenv
Requires-Dist: questionary
Requires-Dist: rich
Requires-Dist: tiktoken
Provides-Extra: dev
Requires-Dist: bump-my-version; extra == 'dev'
Requires-Dist: codecov; extra == 'dev'
Requires-Dist: pytest; extra == 'dev'
Requires-Dist: pytest-cov; extra == 'dev'
Requires-Dist: ruff; extra == 'dev'
